LICENSE
README.md
setup.py
zhou_stattool/__init__.py
zhou_stattool/add_rule_window.py
zhou_stattool/add_rule_window_main.py
zhou_stattool/app.py
zhou_stattool/images_rc.py
zhou_stattool/mainwindow.py
zhou_stattool/roomdata_window.py
zhou_stattool/roomdata_window_main.py
zhou_stattool.egg-info/PKG-INFO
zhou_stattool.egg-info/SOURCES.txt
zhou_stattool.egg-info/dependency_links.txt
zhou_stattool.egg-info/entry_points.txt
zhou_stattool.egg-info/requires.txt
zhou_stattool.egg-info/top_level.txt
zhou_stattool/icons/arrow.png
zhou_stattool/icons/edit.png
zhou_stattool/icons/minus.png
zhou_stattool/icons/open.png
zhou_stattool/icons/plus.png
zhou_stattool/icons/save.png
zhou_stattool/icons/undo.png