Metadata-Version: 2.1
Name: zhou-stattool
Version: 0.0.6
Summary: statistic tool for zhou
Home-page: UNKNOWN
Author: Frederic
Author-email: fk1010098686@outlook.com
License: MIT
Platform: UNKNOWN
Classifier: Development Status :: 5 - Production/Stable
Classifier: Intended Audience :: Developers
Classifier: Natural Language :: English
Classifier: Programming Language :: Python
Classifier: Programming Language :: Python :: 3
Classifier: Programming Language :: Python :: Implementation :: CPython
Classifier: Programming Language :: Python :: Implementation :: PyPy
License-File: LICENSE
